speech_collator/__init__.py
speech_collator/measures/__init__.py
speech_collator/measures/snr.py
speech_collator/measures/srmr.py
speech_collator-0.1.19.dist-info/METADATA
speech_collator-0.1.19.dist-info/WHEEL
speech_collator-0.1.19.dist-info/RECORD
