Metadata-Version: 2.3
Name: speech-collator
Version: 0.1.19
Summary: A collator for speech datasets with different batching strategies and attribute extraction.
Author-email: Christoph Minixhofer <christoph.minixhofer@gmail.com>
License: MIT
Requires-Python: >=3.8
Requires-Dist: librosa<0.10
Requires-Dist: numpy>=1.24
Requires-Dist: pyworld>=0.3.2
Requires-Dist: scipy>=1.9.3
